<package>
  <description brief="cob_generic_states_experimental">

     cob_generic_states_experimental

  </description>
  <author>tys</author>
  <license>BSD</license>
  <review status="unreviewed" notes=""/>
  <url>http://ros.org/wiki/cob_generic_states_experimental</url>
  <depend package="rospy"/>
  <depend package="smach"/>
  <depend package="smach_ros"/>
  <depend package="actionlib_msgs"/>
  <depend package="tf"/>
  <depend package="kinematics_msgs"/>
  <depend package="cob_script_server"/>
  <depend package="cob_object_detection_msgs"/>
  <depend package="cob_object_detection_fake"/>

</package>


